telegram_praisonai_bot/__init__.py
telegram_praisonai_bot/bot.py
telegram_praisonai_bot/client.py
telegram_praisonai_bot-0.1.0.dist-info/licenses/LICENSE
telegram_praisonai_bot-0.1.0.dist-info/METADATA
telegram_praisonai_bot-0.1.0.dist-info/WHEEL
telegram_praisonai_bot-0.1.0.dist-info/entry_points.txt
telegram_praisonai_bot-0.1.0.dist-info/top_level.txt
telegram_praisonai_bot-0.1.0.dist-info/RECORD
