Metadata-Version: 2.4
Name: telegram-praisonai-bot
Version: 0.1.0
Summary: Telegram bot powered by PraisonAI multi-agent framework
Author-email: Mervin Praison <support@praison.ai>
License-Expression: MIT
Project-URL: Homepage, https://github.com/MervinPraison/telegram-praisonai-bot
Project-URL: Documentation, https://docs.praison.ai
Project-URL: Repository, https://github.com/MervinPraison/telegram-praisonai-bot
Keywords: telegram,bot,praisonai,ai-agents,multi-agent,llm
Classifier: Development Status :: 4 - Beta
Classifier: Intended Audience :: Developers
Classifier: Programming Language :: Python :: 3
Classifier: Programming Language :: Python :: 3.9
Classifier: Programming Language :: Python :: 3.10
Classifier: Programming Language :: Python :: 3.11
Classifier: Programming Language :: Python :: 3.12
Requires-Python: >=3.9
License-File: LICENSE
Requires-Dist: python-telegram-bot>=20.0
Requires-Dist: httpx>=0.24.0
Requires-Dist: python-dotenv>=1.0.0
Provides-Extra: dev
Requires-Dist: pytest>=7.0.0; extra == "dev"
Requires-Dist: pytest-asyncio>=0.21.0; extra == "dev"
Requires-Dist: pytest-httpx>=0.21.0; extra == "dev"
Dynamic: license-file
